LICENSE
README.rst
pyproject.toml
setup.py
pylama_dmypy/__init__.py
pylama_dmypy/linter.py
pylama_dmypy.egg-info/PKG-INFO
pylama_dmypy.egg-info/SOURCES.txt
pylama_dmypy.egg-info/dependency_links.txt
pylama_dmypy.egg-info/entry_points.txt
pylama_dmypy.egg-info/requires.txt
pylama_dmypy.egg-info/top_level.txt