Metadata-Version: 2.1
Name: pylama-dmypy
Version: 0.2
Summary: Linting plugin for pylama to see dmypy
Home-page: http://github.com/delfick/pylama-dmypy
Author: Stephen Moore
Author-email: stephen@delfick.com
License: MIT
Platform: UNKNOWN
Provides-Extra: tests
License-File: LICENSE
